LICENSE
MANIFEST.in
README.rst
setup.cfg
setup.py
versioneer.py
tpDcc/__init__.py
tpDcc/libs/__init__.py
tpDcc/libs/plugin/__init__.py
tpDcc/libs/plugin/__logging__.ini
tpDcc/libs/plugin/__version__.py
tpDcc/libs/plugin/_version.py
tpDcc/libs/plugin/core/__init__.py
tpDcc/libs/plugin/core/consts.py
tpDcc/libs/plugin/core/factory.py
tpDcc_libs_plugin.egg-info/PKG-INFO
tpDcc_libs_plugin.egg-info/SOURCES.txt
tpDcc_libs_plugin.egg-info/dependency_links.txt
tpDcc_libs_plugin.egg-info/not-zip-safe
tpDcc_libs_plugin.egg-info/requires.txt
tpDcc_libs_plugin.egg-info/top_level.txt