Metadata-Version: 2.1
Name: tpDcc-libs-plugin
Version: 0.0.1
Summary: Library that contains classes to implement plugin architecture in Python
Home-page: https://github.com/tpDcc/tpDcc-libs-plugin
Author: Tomas Poveda
Author-email: tpovedatd@gmail.com
License: MIT
Platform: UNKNOWN
Provides-Extra: dev
Provides-Extra: test
